hezor_common/__init__.py
hezor_common/py.typed
hezor_common/data_model/__init__.py
hezor_common/data_model/creations/__init__.py
hezor_common/data_model/creations/core/__init__.py
hezor_common/data_model/creations/core/chapter_generate_result.py
hezor_common/data_model/creations/core/chapter_model.py
hezor_common/data_model/creations/core/creation_generate_result.py
hezor_common/data_model/creations/core/creation_model.py
hezor_common/data_model/creations/core/creation_params.py
hezor_common/data_model/creations/core/section_generate_result.py
hezor_common/data_model/creations/core/section_model.py
hezor_common-0.1.3.dist-info/METADATA
hezor_common-0.1.3.dist-info/WHEEL
hezor_common-0.1.3.dist-info/licenses/LICENSE
hezor_common-0.1.3.dist-info/RECORD
