Metadata-Version: 2.4
Name: hezor-common
Version: 0.1.3
Summary: Common utilities and data models for Hezor projects
Project-URL: Homepage, https://github.com/lennon/hezor_common
Project-URL: Repository, https://github.com/lennon/hezor_common
Project-URL: Issues, https://github.com/lennon/hezor_common/issues
Author-email: Silo QIAN <qtisan@hotmail.com>
License-File: LICENSE
Keywords: common,hezor,utilities
Classifier: Development Status :: 3 - Alpha
Classifier: Intended Audience :: Developers
Classifier: License :: OSI Approved :: MIT License
Classifier: Programming Language :: Python :: 3
Classifier: Programming Language :: Python :: 3.11
Classifier: Programming Language :: Python :: 3.12
Classifier: Programming Language :: Python :: 3.13
Requires-Python: >=3.11
Requires-Dist: pydantic>=2.0.0
Provides-Extra: dev
Requires-Dist: bump-my-version; extra == 'dev'
